zexture/GestureMath.py
zexture/HandTrackingModule.py
zexture/__init__.py
zexture/statMode.py
zexture-1.0.1.dist-info/LICENSE
zexture-1.0.1.dist-info/METADATA
zexture-1.0.1.dist-info/WHEEL
zexture-1.0.1.dist-info/entry_points.txt
zexture-1.0.1.dist-info/top_level.txt
zexture-1.0.1.dist-info/RECORD
