Metadata-Version: 2.1
Name: zexture
Version: 1.0.1
Summary: It the number
Home-page: https://github.com/auddy99/Gesture-Detection
Author: Nidhi Singh,Auddy Soumyadeep,Mayank Raj
Author-email: zexture.detection@gmail.com
License: MIT
Platform: UNKNOWN
Classifier: Programming Language :: Python :: 3.8
License-File: LICENSE
Requires-Dist: absl-py (==1.0.0)
Requires-Dist: attrs (==21.4.0)
Requires-Dist: cycler (==0.11.0)
Requires-Dist: fonttools (==4.30.0)
Requires-Dist: joblib (==1.1.0)
Requires-Dist: kiwisolver (==1.3.2)
Requires-Dist: matplotlib (==3.5.1)
Requires-Dist: mediapipe (==0.8.9.1)
Requires-Dist: numpy (==1.22.3)
Requires-Dist: opencv-contrib-python (==4.5.5.64)
Requires-Dist: opencv-python (==4.5.5.64)
Requires-Dist: packaging (==21.3)
Requires-Dist: pandas (==1.4.1)
Requires-Dist: Pillow (==9.0.1)
Requires-Dist: protobuf (==3.19.4)
Requires-Dist: pyparsing (==3.0.7)
Requires-Dist: python-dateutil (==2.8.2)
Requires-Dist: pytz (==2021.3)
Requires-Dist: scikit-learn (==1.0.2)
Requires-Dist: scipy (==1.8.0)
Requires-Dist: six (==1.16.0)
Requires-Dist: threadpoolctl (==3.1.0)
